windockd/__init__.py
windockd/cli.py
windockd/installer.py
windockd/service.py
windockd/utils.py
windockd/resources/__init__.py
windockd/resources/containerd.zip
windockd/resources/nerdctl.zip
windockd-1.1.4.dist-info/METADATA
windockd-1.1.4.dist-info/WHEEL
windockd-1.1.4.dist-info/entry_points.txt
windockd-1.1.4.dist-info/top_level.txt
windockd-1.1.4.dist-info/RECORD
