Metadata-Version: 2.4
Name: windockd
Version: 1.1.4
Summary: Lightweight Windows Container Runtime CLI
Home-page: https://github.com/RohanRusta21/windockd
Author: Your Name
Classifier: Programming Language :: Python :: 3
Classifier: License :: OSI Approved :: MIT License
Classifier: Operating System :: Microsoft :: Windows
Requires-Dist: click>=8.0.0
Dynamic: author
Dynamic: classifier
Dynamic: description
Dynamic: description-content-type
Dynamic: home-page
Dynamic: requires-dist
Dynamic: summary
